datarepo/__init__.py
datarepo/core/__init__.py
datarepo/core/catalog/__init__.py
datarepo/core/catalog/catalog.py
datarepo/core/dataframe/__init__.py
datarepo/core/dataframe/frame.py
datarepo/core/tables/__init__.py
datarepo/core/tables/clickhouse_table.py
datarepo/core/tables/decorator.py
datarepo/core/tables/deltalake_table.py
datarepo/core/tables/filters.py
datarepo/core/tables/metadata.py
datarepo/core/tables/parquet_table.py
datarepo/core/tables/util.py
datarepo/export/__init__.py
datarepo/export/roapi.py
datarepo/export/web.py
datarepo/export/static_site/.gitignore
datarepo/export/static_site/README.md
datarepo/export/static_site/build.py
datarepo/export/static_site/package-lock.json
datarepo/export/static_site/package.json
datarepo/export/static_site/tsconfig.json
datarepo/export/static_site/tsconfig.node.json
datarepo/export/static_site/vite.config.ts
datarepo/export/static_site/precompiled/favicon.png
datarepo/export/static_site/precompiled/index.html
datarepo/export/static_site/precompiled/assets/abap-DsBKuouk.js
datarepo/export/static_site/precompiled/assets/abap-DsBKuouk.js.map
datarepo/export/static_site/precompiled/assets/actionscript-3-D_z4Izcz.js
datarepo/export/static_site/precompiled/assets/actionscript-3-D_z4Izcz.js.map
datarepo/export/static_site/precompiled/assets/ada-727ZlQH0.js
datarepo/export/static_site/precompiled/assets/ada-727ZlQH0.js.map
datarepo/export/static_site/precompiled/assets/andromeeda-C3khCPGq.js
datarepo/export/static_site/precompiled/assets/andromeeda-C3khCPGq.js.map
datarepo/export/static_site/precompiled/assets/angular-html-LfdN0zeE.js
datarepo/export/static_site/precompiled/assets/angular-html-LfdN0zeE.js.map
datarepo/export/static_site/precompiled/assets/angular-ts-CKsD7JZE.js
datarepo/export/static_site/precompiled/assets/angular-ts-CKsD7JZE.js.map
datarepo/export/static_site/precompiled/assets/apache-Dn00JSTd.js
datarepo/export/static_site/precompiled/assets/apache-Dn00JSTd.js.map
data_repository-0.0.2.dist-info/METADATA
data_repository-0.0.2.dist-info/WHEEL
data_repository-0.0.2.dist-info/licenses/LICENSE.md
data_repository-0.0.2.dist-info/RECORD
