Metadata-Version: 2.4
Name: data-repository
Version: 0.0.2
Summary: A simple platform for complex data
Project-URL: Homepage, https://github.com/neuralinkcorp/datarepo
Project-URL: Issues, https://github.com/neuralinkcorp/datarepo/issues
Author-email: Gautham Acharya <gautacharya@gmail.com>
License: Apache-2.0
License-File: LICENSE.md
Classifier: Development Status :: 5 - Production/Stable
Classifier: License :: OSI Approved :: Apache Software License
Classifier: Operating System :: OS Independent
Classifier: Programming Language :: Python :: 3
Requires-Python: >=3.8
Requires-Dist: boto3>=1.26.20
Requires-Dist: deltalake<1,>=0.25.4
Requires-Dist: ipython>=8.5.0
Requires-Dist: polars<1.14.0,>=1.9.0
Requires-Dist: pyarrow>=17.0.0
Provides-Extra: dev
Requires-Dist: black>=23.0.0; extra == 'dev'
Requires-Dist: boto3-stubs>=1.39.0; extra == 'dev'
Requires-Dist: flake8>=6.0.0; extra == 'dev'
Requires-Dist: mkdocs-material>=9.6.14; extra == 'dev'
Requires-Dist: mkdocs>=1.5.0; extra == 'dev'
Requires-Dist: mkdocstrings-python>=1.7.0; extra == 'dev'
Requires-Dist: mkdocstrings>=0.29.1; extra == 'dev'
Requires-Dist: mypy>=1.0.0; extra == 'dev'
Requires-Dist: pyarrow-stubs>=20.0.0; extra == 'dev'
Requires-Dist: pytest-cov>=4.0.0; extra == 'dev'
Requires-Dist: pytest>=7.0.0; extra == 'dev'
